[
  { "path": "/about",    "label": { "en": "ABOUT", "zh": "关于", "de": "ÜBER" },                  "display": true },
  { "path": "/research", "label": { "en": "RESEARCH", "zh": "研究", "de": "FORSCHUNG" },          "display": true },
  { "path": "/music",    "label": { "en": "MUSIC", "zh": "音乐", "de": "MUSIK" },                 "display": true },
  { "path": "/blog",     "label": { "en": "BLOG", "zh": "博客", "de": "BLOG" },                   "display": false },
  { "path": "/projects", "label": { "en": "PROJECTS", "zh": "项目", "de": "PROJEKTE" },           "display": false },
  { "path": "/misc",     "label": { "en": "MISCELLANEOUS", "zh": "杂项", "de": "VERSCHIEDENES" }, "display": false }
]
